super_scad/__init__.py
super_scad/boolean/Compound.py
super_scad/boolean/Difference.py
super_scad/boolean/Empty.py
super_scad/boolean/Intersection.py
super_scad/boolean/Union.py
super_scad/boolean/__init__.py
super_scad/d0/Import.py
super_scad/d0/__init__.py
super_scad/d2/Circle.py
super_scad/d2/Polygon.py
super_scad/d2/PolygonMixin.py
super_scad/d2/Projection.py
super_scad/d2/Rectangle.py
super_scad/d2/Semicircle.py
super_scad/d2/Square.py
super_scad/d2/Text.py
super_scad/d2/__init__.py
super_scad/d2/helper/PolygonSideExtender.py
super_scad/d2/helper/__init__.py
super_scad/d2/private/PrivateCircle.py
super_scad/d2/private/PrivatePolygon.py
super_scad/d2/private/PrivateProjection.py
super_scad/d2/private/PrivateSquare.py
super_scad/d2/private/__init__.py
super_scad/d3/Cone.py
super_scad/d3/Cube.py
super_scad/d3/Cuboid.py
super_scad/d3/Cylinder.py
super_scad/d3/LinearExtrude.py
super_scad/d3/Polyhedron.py
super_scad/d3/RotateExtrude.py
super_scad/d3/Sphere.py
super_scad/d3/Surface.py
super_scad/d3/__init__.py
super_scad/d3/private/PrivateCube.py
super_scad/d3/private/PrivateCylinder.py
super_scad/d3/private/PrivateLinearExtrude.py
super_scad/d3/private/PrivatePolyhedron.py
super_scad/d3/private/PrivateSphere.py
super_scad/d3/private/__init__.py
super_scad/other/Echo.py
super_scad/other/Modify.py
super_scad/other/Render.py
super_scad/other/__init__.py
super_scad/private/PrivateMultiChildOpenScadCommand.py
super_scad/private/PrivateOpenScadCommand.py
super_scad/private/PrivateSingleChildOpenScadCommand.py
super_scad/private/__init__.py
super_scad/scad/ArgumentValidator.py
super_scad/scad/BOM.py
super_scad/scad/Context.py
super_scad/scad/Length.py
super_scad/scad/Scad.py
super_scad/scad/ScadCodeStore.py
super_scad/scad/ScadMultiChildParent.py
super_scad/scad/ScadSingleChildParent.py
super_scad/scad/ScadWidget.py
super_scad/scad/Unit.py
super_scad/scad/__init__.py
super_scad/scad/unit/AngstromUnit.py
super_scad/scad/unit/AstronomicalUnit.py
super_scad-0.11.6.dist-info/METADATA
super_scad-0.11.6.dist-info/WHEEL
super_scad-0.11.6.dist-info/licenses/LICENSE
super_scad-0.11.6.dist-info/RECORD
