Metadata-Version: 2.4
Name: Super-SCAD
Version: 0.11.6
Summary: An advanced Python application and library for generating 2D and 3D models in OpenSCAD
License: MIT
License-File: LICENSE
Keywords: OpenSCAD,SuperSCAD
Author: P.R. Water
Author-email: p.r.water@setbased.nl
Requires-Python: >=3.13.0,<4.0.0
Classifier: Development Status :: 5 - Production/Stable
Classifier: Intended Audience :: Developers
Classifier: Intended Audience :: Manufacturing
Classifier: License :: OSI Approved :: MIT License
Classifier: Programming Language :: Python :: 3
Classifier: Programming Language :: Python :: 3.13
Classifier: Programming Language :: Python :: 3.14
Classifier: Topic :: Multimedia :: Graphics :: 3D Modeling
Classifier: Topic :: Software Development :: Code Generators
Project-URL: Documentation, https://www.superscad.org/
Project-URL: Repository, https://github.com/SuperSCAD/SuperSCAD
